Metadata-Version: 1.1
Name: ridi-test
Version: 0.0.1
Summary: Ridi TEST
Home-page: https://github.com/ridi/cms-sdk
Author: UNKNOWN
Author-email: UNKNOWN
License: UNKNOWN
Keywords: ridi,ridibooks
Platform: UNKNOWN
Classifier: License :: OSI Approved :: MIT License
Classifier: Programming Language :: Python :: 3
